fastaio/__init__.py
fastaio/_cli.py
fastaio/_config.py
fastaio/_container.py
fastaio/_importer.py
fastaio/_module.py
fastaio/py.typed
fastaio/web/fastapi.py
fastaio-0.5.0.dist-info/METADATA
fastaio-0.5.0.dist-info/WHEEL
fastaio-0.5.0.dist-info/entry_points.txt
fastaio-0.5.0.dist-info/licenses/LICENSE
fastaio-0.5.0.dist-info/RECORD
