Metadata-Version: 2.4
Name: fastaio
Version: 0.5.0
Summary: A system for creating modular, configurable, pluggable and concurrent applications
Project-URL: Source, https://github.com/davidbrochart/fastaio
Project-URL: Issues, https://github.com/davidbrochart/fastaio/issues
Author-email: David Brochart <david.brochart@gmail.com>
License: BSD 3-Clause License
License-File: LICENSE
Classifier: Development Status :: 4 - Beta
Classifier: Intended Audience :: Developers
Classifier: License :: OSI Approved :: BSD License
Classifier: Programming Language :: Python
Classifier: Programming Language :: Python :: 3
Classifier: Programming Language :: Python :: 3.9
Classifier: Programming Language :: Python :: 3.10
Classifier: Programming Language :: Python :: 3.11
Classifier: Programming Language :: Python :: 3.12
Classifier: Programming Language :: Python :: 3.13
Classifier: Typing :: Typed
Requires-Python: >=3.9
Requires-Dist: anyio
Requires-Dist: anyioutils>=0.4.9
Requires-Dist: click<9,>=8.1.8
Requires-Dist: exceptiongroup; python_version < '3.11'
Requires-Dist: importlib-metadata>=3.6; python_version < '3.10'
Requires-Dist: structlog
Provides-Extra: test
Requires-Dist: coverage[toml]<8,>=7; extra == 'test'
Requires-Dist: httpx; extra == 'test'
Requires-Dist: mypy; extra == 'test'
Requires-Dist: pytest<9,>=8; extra == 'test'
Requires-Dist: ruff; extra == 'test'
Requires-Dist: trio<0.28,>=0.27.0; extra == 'test'
Provides-Extra: web
Requires-Dist: anycorn; extra == 'web'
Requires-Dist: fastapi; extra == 'web'
